c4m/__init__.py
c4m/flexmem/__init__.py
c4m/flexmem/common.py
c4m/flexmem/dp8t/__init__.py
c4m/flexmem/dp8t/factory.py
c4m/flexmem/dp8t/sramcelldp8t.py
c4m/flexmem/sp6t/__init__.py
c4m/flexmem/sp6t/factory.py
c4m/flexmem/sp6t/sramcellsp6t.py
c4m_flexmem-0.1.0.dist-info/LICENSE.md
c4m_flexmem-0.1.0.dist-info/METADATA
c4m_flexmem-0.1.0.dist-info/WHEEL
c4m_flexmem-0.1.0.dist-info/top_level.txt
c4m_flexmem-0.1.0.dist-info/RECORD
