Metadata-Version: 2.1
Name: c4m-flexmem
Version: 0.1.0
Summary: PDKMaster based scalable memory macro generators
Author: Staf Verhaegen
Author-email: staf@fibraservi.eu
License: multi
Project-URL: Source Code, https://gitlab.com/Chips4Makers/c4m-flexmem
Project-URL: Bug Tracker, https://gitlab.com/Chips4Makers/c4m-flexmem/issues
Requires-Python: ~=3.6
License-File: LICENSE.md
Requires-Dist: setuptools
Requires-Dist: PDKMaster (==0.9.*)
Requires-Dist: c4m-flexcell (==0.3.*)
